AUTHORS
ChangeLog
setup.cfg
setup.py
createpy/__init__.py
createpy/createpy.py
createpy.egg-info/PKG-INFO
createpy.egg-info/SOURCES.txt
createpy.egg-info/dependency_links.txt
createpy.egg-info/entry_points.txt
createpy.egg-info/not-zip-safe
createpy.egg-info/pbr.json
createpy.egg-info/top_level.txt