Metadata-Version: 1.1
Name: createpy
Version: 0.0.0
Summary: OpenStack's setup automation in a reusable form
Home-page: https://launchpad.net/pbr
Author: 'Steven Cooney'
Author-email: flyingcircus@example.com
License: MIT
Platform: UNKNOWN
Classifier: Development Status :: 3 - Alpha
Classifier: Programming Language :: Python :: 3.5
Classifier: Topic :: Text Processing :: Linguistic
